cik/CloseFormIK.cp39-win_amd64.pyd
cik/CloseFormIK.cpython-39-x86_64-linux-gnu.so
cik/__init__.py
robot6Ik-1.0.1.dist-info/METADATA
robot6Ik-1.0.1.dist-info/WHEEL
robot6Ik-1.0.1.dist-info/top_level.txt
robot6Ik-1.0.1.dist-info/RECORD
